prefect_aws_batch/__init__.py
prefect_aws_batch/cli.py
prefect_aws_batch-0.1.0.dist-info/LICENSE
prefect_aws_batch-0.1.0.dist-info/METADATA
prefect_aws_batch-0.1.0.dist-info/WHEEL
prefect_aws_batch-0.1.0.dist-info/entry_points.txt
prefect_aws_batch-0.1.0.dist-info/top_level.txt
prefect_aws_batch-0.1.0.dist-info/RECORD
