Metadata-Version: 2.1
Name: prefect-aws-batch
Version: 0.1.0
Summary: Utilities for interacting with AWS Batch
Home-page: https://github.com/dabble-of-devop-bioanalyze/prefect_aws_batch
Author: Audrey Roy Greenfeld
Author-email: jillian@dabbleofdevops.com
License: Apache Software License 2.0
Keywords: prefect_aws_batch
Classifier: Development Status :: 2 - Pre-Alpha
Classifier: Intended Audience :: Developers
Classifier: License :: OSI Approved :: Apache Software License
Classifier: Natural Language :: English
Classifier: Programming Language :: Python :: 3
Classifier: Programming Language :: Python :: 3.6
Classifier: Programming Language :: Python :: 3.7
Classifier: Programming Language :: Python :: 3.8
Requires-Python: >=3.6
License-File: LICENSE
Requires-Dist: Click (>=7.0)
